{
  "version": "0.18.0", 
  "datetime_saved": "2024-01-30T20:01:54.212368+01:00", 
  "data": {
    "datatype": "RecordKeeper", 
    "currencies": [], 
    "base_currency_code": null, 
    "exchange_rates": [], 
    "securities": [], 
    "account_groups": [], 
    "accounts": [], 
    "root_account_items": [], 
    "payees": [], 
    "tags": [], 
    "categories": [
      {
        "datatype": "Category", 
        "path": "Bydlení", 
        "type": "EXPENSE", 
        "index": null
      }, 
      {
        "datatype": "Category", 
        "path": "Bydlení/Hotel", 
        "type": "EXPENSE", 
        "index": 5
      }, 
      {
        "datatype": "Category", 
        "path": "Bydlení/Nájem", 
        "type": "EXPENSE", 
        "index": 0
      }, 
      {
        "datatype": "Category", 
        "path": "Bydlení/Rekonstrukce", 
        "type": "EXPENSE", 
        "index": 3
      }, 
      {
        "datatype": "Category", 
        "path": "Bydlení/Vybavení", 
        "type": "EXPENSE", 
        "index": 4
      }, 
      {
        "datatype": "Category", 
        "path": "Bydlení/Vybavení/Kuchyň", 
        "type": "EXPENSE", 
        "index": 1
      }, 
      {
        "datatype": "Category", 
        "path": "Bydlení/Vybavení/Nábytek", 
        "type": "EXPENSE", 
        "index": 0
      }, 
      {
        "datatype": "Category", 
        "path": "Bydlení/Vybavení/Opravy", 
        "type": "EXPENSE", 
        "index": 2
      }, 
      {
        "datatype": "Category", 
        "path": "Bydlení/Údržba", 
        "type": "EXPENSE", 
        "index": 6
      }, 
      {
        "datatype": "Category", 
        "path": "Bydlení/Úrok hypotéky", 
        "type": "EXPENSE", 
        "index": 1
      }, 
      {
        "datatype": "Category", 
        "path": "Bydlení/Účty", 
        "type": "EXPENSE", 
        "index": 2
      }, 
      {
        "datatype": "Category", 
        "path": "Bydlení/Účty/Elektřina", 
        "type": "EXPENSE", 
        "index": 0
      }, 
      {
        "datatype": "Category", 
        "path": "Bydlení/Účty/Odpad", 
        "type": "EXPENSE", 
        "index": 3
      }, 
      {
        "datatype": "Category", 
        "path": "Bydlení/Účty/Teplo", 
        "type": "EXPENSE", 
        "index": 1
      }, 
      {
        "datatype": "Category", 
        "path": "Bydlení/Účty/Voda", 
        "type": "EXPENSE", 
        "index": 2
      }, 
      {
        "datatype": "Category", 
        "path": "Daně", 
        "type": "EXPENSE", 
        "index": null
      }, 
      {
        "datatype": "Category", 
        "path": "Dar", 
        "type": "INCOME_AND_EXPENSE", 
        "index": null
      }, 
      {
        "datatype": "Category", 
        "path": "Dar/Aktivity", 
        "type": "INCOME_AND_EXPENSE", 
        "index": 6
      }, 
      {
        "datatype": "Category", 
        "path": "Dar/Finance", 
        "type": "INCOME_AND_EXPENSE", 
        "index": 0
      }, 
      {
        "datatype": "Category", 
        "path": "Dar/Hračky", 
        "type": "INCOME_AND_EXPENSE", 
        "index": 3
      }, 
      {
        "datatype": "Category", 
        "path": "Dar/Jídlo", 
        "type": "INCOME_AND_EXPENSE", 
        "index": 2
      }, 
      {
        "datatype": "Category", 
        "path": "Dar/Květiny", 
        "type": "INCOME_AND_EXPENSE", 
        "index": 4
      }, 
      {
        "datatype": "Category", 
        "path": "Dar/Nápoje", 
        "type": "INCOME_AND_EXPENSE", 
        "index": 1
      }, 
      {
        "datatype": "Category", 
        "path": "Dar/Šperky", 
        "type": "INCOME_AND_EXPENSE", 
        "index": 5
      }, 
      {
        "datatype": "Category", 
        "path": "Digitální zboží", 
        "type": "EXPENSE", 
        "index": null
      }, 
      {
        "datatype": "Category", 
        "path": "Digitální zboží/Cloudové uložiště", 
        "type": "EXPENSE", 
        "index": 2
      }, 
      {
        "datatype": "Category", 
        "path": "Digitální zboží/Internet", 
        "type": "EXPENSE", 
        "index": 0
      }, 
      {
        "datatype": "Category", 
        "path": "Digitální zboží/Mobilní data", 
        "type": "EXPENSE", 
        "index": 1
      }, 
      {
        "datatype": "Category", 
        "path": "Digitální zboží/Mobilní tarif", 
        "type": "EXPENSE", 
        "index": 4
      }, 
      {
        "datatype": "Category", 
        "path": "Digitální zboží/Software", 
        "type": "EXPENSE", 
        "index": 3
      }, 
      {
        "datatype": "Category", 
        "path": "Dividenda", 
        "type": "INCOME", 
        "index": null
      }, 
      {
        "datatype": "Category", 
        "path": "Dobročinnost", 
        "type": "EXPENSE", 
        "index": null
      }, 
      {
        "datatype": "Category", 
        "path": "Domácí potřeby", 
        "type": "EXPENSE", 
        "index": null
      }, 
      {
        "datatype": "Category", 
        "path": "Doprava", 
        "type": "EXPENSE", 
        "index": null
      }, 
      {
        "datatype": "Category", 
        "path": "Doprava/Auto", 
        "type": "EXPENSE", 
        "index": 0
      }, 
      {
        "datatype": "Category", 
        "path": "Doprava/Auto/Koupě", 
        "type": "EXPENSE", 
        "index": 1
      }, 
      {
        "datatype": "Category", 
        "path": "Doprava/Auto/Mýto", 
        "type": "EXPENSE", 
        "index": 5
      }, 
      {
        "datatype": "Category", 
        "path": "Doprava/Auto/Palivo", 
        "type": "EXPENSE", 
        "index": 0
      }, 
      {
        "datatype": "Category", 
        "path": "Doprava/Auto/Parkování", 
        "type": "EXPENSE", 
        "index": 3
      }, 
      {
        "datatype": "Category", 
        "path": "Doprava/Auto/Pojištění", 
        "type": "EXPENSE", 
        "index": 6
      }, 
      {
        "datatype": "Category", 
        "path": "Doprava/Auto/Pronájem", 
        "type": "EXPENSE", 
        "index": 4
      }, 
      {
        "datatype": "Category", 
        "path": "Doprava/Auto/Údržba", 
        "type": "EXPENSE", 
        "index": 2
      }, 
      {
        "datatype": "Category", 
        "path": "Doprava/Bus", 
        "type": "EXPENSE", 
        "index": 3
      }, 
      {
        "datatype": "Category", 
        "path": "Doprava/Car sharing", 
        "type": "EXPENSE", 
        "index": 2
      }, 
      {
        "datatype": "Category", 
        "path": "Doprava/Letadlo", 
        "type": "EXPENSE", 
        "index": 5
      }, 
      {
        "datatype": "Category", 
        "path": "Doprava/Loď", 
        "type": "EXPENSE", 
        "index": 6
      }, 
      {
        "datatype": "Category", 
        "path": "Doprava/Taxi", 
        "type": "EXPENSE", 
        "index": 7
      }, 
      {
        "datatype": "Category", 
        "path": "Doprava/Veřejná", 
        "type": "EXPENSE", 
        "index": 1
      }, 
      {
        "datatype": "Category", 
        "path": "Doprava/Vlak", 
        "type": "EXPENSE", 
        "index": 4
      }, 
      {
        "datatype": "Category", 
        "path": "Drogerie", 
        "type": "EXPENSE", 
        "index": null
      }, 
      {
        "datatype": "Category", 
        "path": "Drogerie/Kosmetika", 
        "type": "EXPENSE", 
        "index": 0
      }, 
      {
        "datatype": "Category", 
        "path": "Drogerie/Péče o kůži", 
        "type": "EXPENSE", 
        "index": 1
      }, 
      {
        "datatype": "Category", 
        "path": "Drogerie/Péče o vlasy", 
        "type": "EXPENSE", 
        "index": 2
      }, 
      {
        "datatype": "Category", 
        "path": "Dědictví", 
        "type": "INCOME", 
        "index": null
      }, 
      {
        "datatype": "Category", 
        "path": "Electronika", 
        "type": "EXPENSE", 
        "index": null
      }, 
      {
        "datatype": "Category", 
        "path": "Jiné příjmy", 
        "type": "INCOME", 
        "index": null
      }, 
      {
        "datatype": "Category", 
        "path": "Mazlíčci", 
        "type": "EXPENSE", 
        "index": null
      }, 
      {
        "datatype": "Category", 
        "path": "Mazlíčci/Jídlo", 
        "type": "EXPENSE", 
        "index": 1
      }, 
      {
        "datatype": "Category", 
        "path": "Mazlíčci/Koupě", 
        "type": "EXPENSE", 
        "index": 0
      }, 
      {
        "datatype": "Category", 
        "path": "Mazlíčci/Veterinář", 
        "type": "EXPENSE", 
        "index": 2
      }, 
      {
        "datatype": "Category", 
        "path": "Oblečení", 
        "type": "EXPENSE", 
        "index": null
      }, 
      {
        "datatype": "Category", 
        "path": "Oblečení/Běžné", 
        "type": "EXPENSE", 
        "index": 0
      }, 
      {
        "datatype": "Category", 
        "path": "Oblečení/Doplňky", 
        "type": "EXPENSE", 
        "index": 2
      }, 
      {
        "datatype": "Category", 
        "path": "Oblečení/Formální", 
        "type": "EXPENSE", 
        "index": 1
      }, 
      {
        "datatype": "Category", 
        "path": "Oblečení/Obuv", 
        "type": "EXPENSE", 
        "index": 3
      }, 
      {
        "datatype": "Category", 
        "path": "Podnikání", 
        "type": "INCOME", 
        "index": null
      }, 
      {
        "datatype": "Category", 
        "path": "Pojištění", 
        "type": "EXPENSE", 
        "index": null
      }, 
      {
        "datatype": "Category", 
        "path": "Pojištění/Cestovní", 
        "type": "EXPENSE", 
        "index": 3
      }, 
      {
        "datatype": "Category", 
        "path": "Pojištění/Majetku", 
        "type": "EXPENSE", 
        "index": 1
      }, 
      {
        "datatype": "Category", 
        "path": "Pojištění/Nemovitosti", 
        "type": "EXPENSE", 
        "index": 4
      }, 
      {
        "datatype": "Category", 
        "path": "Pojištění/Právní ochrana", 
        "type": "EXPENSE", 
        "index": 2
      }, 
      {
        "datatype": "Category", 
        "path": "Pojištění/Životní", 
        "type": "EXPENSE", 
        "index": 0
      }, 
      {
        "datatype": "Category", 
        "path": "Práce", 
        "type": "EXPENSE", 
        "index": null
      }, 
      {
        "datatype": "Category", 
        "path": "Práce/Kancelářské potřeby", 
        "type": "EXPENSE", 
        "index": 0
      }, 
      {
        "datatype": "Category", 
        "path": "Práce/Členský příspěvek", 
        "type": "EXPENSE", 
        "index": 2
      }, 
      {
        "datatype": "Category", 
        "path": "Práce/Školení a konference", 
        "type": "EXPENSE", 
        "index": 1
      }, 
      {
        "datatype": "Category", 
        "path": "Půjčka", 
        "type": "INCOME_AND_EXPENSE", 
        "index": null
      }, 
      {
        "datatype": "Category", 
        "path": "Služby", 
        "type": "EXPENSE", 
        "index": null
      }, 
      {
        "datatype": "Category", 
        "path": "Služby/Barber", 
        "type": "EXPENSE", 
        "index": 1
      }, 
      {
        "datatype": "Category", 
        "path": "Služby/Catering", 
        "type": "EXPENSE", 
        "index": 4
      }, 
      {
        "datatype": "Category", 
        "path": "Služby/Finanční", 
        "type": "EXPENSE", 
        "index": 3
      }, 
      {
        "datatype": "Category", 
        "path": "Služby/Kadeřnice", 
        "type": "EXPENSE", 
        "index": 0
      }, 
      {
        "datatype": "Category", 
        "path": "Služby/Pošta", 
        "type": "EXPENSE", 
        "index": 5
      }, 
      {
        "datatype": "Category", 
        "path": "Služby/Právní", 
        "type": "EXPENSE", 
        "index": 8
      }, 
      {
        "datatype": "Category", 
        "path": "Služby/Realitní", 
        "type": "EXPENSE", 
        "index": 9
      }, 
      {
        "datatype": "Category", 
        "path": "Služby/Tisk", 
        "type": "EXPENSE", 
        "index": 2
      }, 
      {
        "datatype": "Category", 
        "path": "Služby/Toalety", 
        "type": "EXPENSE", 
        "index": 6
      }, 
      {
        "datatype": "Category", 
        "path": "Služby/Řemeslník", 
        "type": "EXPENSE", 
        "index": 7
      }, 
      {
        "datatype": "Category", 
        "path": "Sociální dávky", 
        "type": "INCOME", 
        "index": null
      }, 
      {
        "datatype": "Category", 
        "path": "Sport", 
        "type": "EXPENSE", 
        "index": null
      }, 
      {
        "datatype": "Category", 
        "path": "Sport/Aktivity", 
        "type": "EXPENSE", 
        "index": 2
      }, 
      {
        "datatype": "Category", 
        "path": "Sport/Oblečení", 
        "type": "EXPENSE", 
        "index": 1
      }, 
      {
        "datatype": "Category", 
        "path": "Sport/Vybavení", 
        "type": "EXPENSE", 
        "index": 0
      }, 
      {
        "datatype": "Category", 
        "path": "Stipendium", 
        "type": "INCOME", 
        "index": null
      }, 
      {
        "datatype": "Category", 
        "path": "Strava", 
        "type": "EXPENSE", 
        "index": null
      }, 
      {
        "datatype": "Category", 
        "path": "Strava/Alkohol", 
        "type": "EXPENSE", 
        "index": 3
      }, 
      {
        "datatype": "Category", 
        "path": "Strava/Dovoz", 
        "type": "EXPENSE", 
        "index": 2
      }, 
      {
        "datatype": "Category", 
        "path": "Strava/Nákup", 
        "type": "EXPENSE", 
        "index": 0
      }, 
      {
        "datatype": "Category", 
        "path": "Strava/Restaurace", 
        "type": "EXPENSE", 
        "index": 1
      }, 
      {
        "datatype": "Category", 
        "path": "Sázka", 
        "type": "INCOME_AND_EXPENSE", 
        "index": null
      }, 
      {
        "datatype": "Category", 
        "path": "Volný čas", 
        "type": "EXPENSE", 
        "index": null
      }, 
      {
        "datatype": "Category", 
        "path": "Volný čas/Koníčky", 
        "type": "EXPENSE", 
        "index": 3
      }, 
      {
        "datatype": "Category", 
        "path": "Volný čas/Koníčky/DIY", 
        "type": "EXPENSE", 
        "index": 0
      }, 
      {
        "datatype": "Category", 
        "path": "Volný čas/Koníčky/Deskovky", 
        "type": "EXPENSE", 
        "index": 2
      }, 
      {
        "datatype": "Category", 
        "path": "Volný čas/Koníčky/Videohry", 
        "type": "EXPENSE", 
        "index": 3
      }, 
      {
        "datatype": "Category", 
        "path": "Volný čas/Koníčky/Zahrada", 
        "type": "EXPENSE", 
        "index": 1
      }, 
      {
        "datatype": "Category", 
        "path": "Volný čas/Kultura", 
        "type": "EXPENSE", 
        "index": 0
      }, 
      {
        "datatype": "Category", 
        "path": "Volný čas/Kultura/Divadlo", 
        "type": "EXPENSE", 
        "index": 1
      }, 
      {
        "datatype": "Category", 
        "path": "Volný čas/Kultura/Hudba", 
        "type": "EXPENSE", 
        "index": 4
      }, 
      {
        "datatype": "Category", 
        "path": "Volný čas/Kultura/Kino", 
        "type": "EXPENSE", 
        "index": 0
      }, 
      {
        "datatype": "Category", 
        "path": "Volný čas/Kultura/Muzea, galeria", 
        "type": "EXPENSE", 
        "index": 2
      }, 
      {
        "datatype": "Category", 
        "path": "Volný čas/Kultura/Památky", 
        "type": "EXPENSE", 
        "index": 3
      }, 
      {
        "datatype": "Category", 
        "path": "Volný čas/Kultura/Předplatné", 
        "type": "EXPENSE", 
        "index": 5
      }, 
      {
        "datatype": "Category", 
        "path": "Volný čas/Wellness", 
        "type": "EXPENSE", 
        "index": 2
      }, 
      {
        "datatype": "Category", 
        "path": "Volný čas/Četba", 
        "type": "EXPENSE", 
        "index": 1
      }, 
      {
        "datatype": "Category", 
        "path": "Volný čas/Četba/Knihy", 
        "type": "EXPENSE", 
        "index": 2
      }, 
      {
        "datatype": "Category", 
        "path": "Volný čas/Četba/Noviny", 
        "type": "EXPENSE", 
        "index": 1
      }, 
      {
        "datatype": "Category", 
        "path": "Volný čas/Četba/Časopisy", 
        "type": "EXPENSE", 
        "index": 0
      }, 
      {
        "datatype": "Category", 
        "path": "Vratka daně", 
        "type": "INCOME", 
        "index": null
      }, 
      {
        "datatype": "Category", 
        "path": "Vyrovnání účtů", 
        "type": "INCOME_AND_EXPENSE", 
        "index": null
      }, 
      {
        "datatype": "Category", 
        "path": "Vzdělávání", 
        "type": "EXPENSE", 
        "index": null
      }, 
      {
        "datatype": "Category", 
        "path": "Vzdělávání/Knihy", 
        "type": "EXPENSE", 
        "index": 4
      }, 
      {
        "datatype": "Category", 
        "path": "Vzdělávání/Kurzy", 
        "type": "EXPENSE", 
        "index": 0
      }, 
      {
        "datatype": "Category", 
        "path": "Vzdělávání/Pomůcky", 
        "type": "EXPENSE", 
        "index": 1
      }, 
      {
        "datatype": "Category", 
        "path": "Vzdělávání/Software", 
        "type": "EXPENSE", 
        "index": 3
      }, 
      {
        "datatype": "Category", 
        "path": "Vzdělávání/Školné", 
        "type": "EXPENSE", 
        "index": 2
      }, 
      {
        "datatype": "Category", 
        "path": "Zaměstnání", 
        "type": "INCOME", 
        "index": null
      }, 
      {
        "datatype": "Category", 
        "path": "Zaměstnání/Bonus", 
        "type": "INCOME", 
        "index": 1
      }, 
      {
        "datatype": "Category", 
        "path": "Zaměstnání/Jiné benefity", 
        "type": "INCOME", 
        "index": 4
      }, 
      {
        "datatype": "Category", 
        "path": "Zaměstnání/Mzda", 
        "type": "INCOME", 
        "index": 0
      }, 
      {
        "datatype": "Category", 
        "path": "Zaměstnání/Penzijní spoření", 
        "type": "INCOME", 
        "index": 3
      }, 
      {
        "datatype": "Category", 
        "path": "Zaměstnání/Stravenky", 
        "type": "INCOME", 
        "index": 2
      }, 
      {
        "datatype": "Category", 
        "path": "Zdraví", 
        "type": "EXPENSE", 
        "index": null
      }, 
      {
        "datatype": "Category", 
        "path": "Zdraví/Doplňky", 
        "type": "EXPENSE", 
        "index": 1
      }, 
      {
        "datatype": "Category", 
        "path": "Zdraví/Léky", 
        "type": "EXPENSE", 
        "index": 0
      }, 
      {
        "datatype": "Category", 
        "path": "Zdraví/Očkování", 
        "type": "EXPENSE", 
        "index": 2
      }, 
      {
        "datatype": "Category", 
        "path": "Zdraví/Praktik", 
        "type": "EXPENSE", 
        "index": 4
      }, 
      {
        "datatype": "Category", 
        "path": "Zdraví/Zubař", 
        "type": "EXPENSE", 
        "index": 3
      }, 
      {
        "datatype": "Category", 
        "path": "Úrok", 
        "type": "INCOME_AND_EXPENSE", 
        "index": null
      }
    ], 
    "root_income_categories": [
      "Zaměstnání", 
      "Vratka daně", 
      "Stipendium", 
      "Dědictví", 
      "Sociální dávky", 
      "Dividenda", 
      "Podnikání", 
      "Jiné příjmy"
    ], 
    "root_expense_categories": [
      "Bydlení", 
      "Strava", 
      "Volný čas", 
      "Daně", 
      "Doprava", 
      "Práce", 
      "Digitální zboží", 
      "Sport", 
      "Mazlíčci", 
      "Drogerie", 
      "Zdraví", 
      "Pojištění", 
      "Služby", 
      "Oblečení", 
      "Electronika", 
      "Vzdělávání", 
      "Dobročinnost", 
      "Domácí potřeby"
    ], 
    "root_income_and_expense_categories": [
      "Dar", 
      "Úrok", 
      "Půjčka", 
      "Vyrovnání účtů", 
      "Sázka"
    ], 
    "transactions": []
  }
}